fastrepo/__init__.py
fastrepo/__main__.py
fastrepo/cli.py
fastrepo/templates/default/cookiecutter.json
fastrepo/templates/default/hooks/post_gen_project.py
fastrepo/templates/default/hooks/pre_gen_project.py
fastrepo/templates/default/{{cookiecutter.project_slug}}/.azuredevops/pull_request_template/bug.md
fastrepo/templates/default/{{cookiecutter.project_slug}}/.azuredevops/pull_request_template/feature.md
fastrepo/templates/default/{{cookiecutter.project_slug}}/.azuredevops/pull_request_template/improvement.md
fastrepo/templates/default/{{cookiecutter.project_slug}}/.dockerignore
fastrepo/templates/default/{{cookiecutter.project_slug}}/.gitignore
fastrepo/templates/default/{{cookiecutter.project_slug}}/.gitlab/merge_request_templates/bug.md
fastrepo/templates/default/{{cookiecutter.project_slug}}/.gitlab/merge_request_templates/feature.md
fastrepo/templates/default/{{cookiecutter.project_slug}}/.gitlab/merge_request_templates/improvement.md
fastrepo/templates/default/{{cookiecutter.project_slug}}/.gitlab-ci.yml
fastrepo/templates/default/{{cookiecutter.project_slug}}/.gitpod.Dockerfile
fastrepo/templates/default/{{cookiecutter.project_slug}}/.gitpod.yml
fastrepo/templates/default/{{cookiecutter.project_slug}}/.pre-commit-config.yaml
fastrepo/templates/default/{{cookiecutter.project_slug}}/.vscode/settings.json
fastrepo/templates/default/{{cookiecutter.project_slug}}/README.md
fastrepo/templates/default/{{cookiecutter.project_slug}}/ci/Dockerfile
fastrepo/templates/default/{{cookiecutter.project_slug}}/docs/apidoc/index.md
fastrepo/templates/default/{{cookiecutter.project_slug}}/docs/index.md
fastrepo/templates/default/{{cookiecutter.project_slug}}/docs/release-notes.md
fastrepo/templates/default/{{cookiecutter.project_slug}}/mkdocs.yml
fastrepo/templates/default/{{cookiecutter.project_slug}}/mypy.ini
fastrepo/templates/default/{{cookiecutter.project_slug}}/notebooks/.gitkeep
fastrepo/templates/default/{{cookiecutter.project_slug}}/pyproject.toml
fastrepo-1.4.0.dist-info/entry_points.txt
fastrepo-1.4.0.dist-info/WHEEL
fastrepo-1.4.0.dist-info/METADATA
fastrepo-1.4.0.dist-info/RECORD
